ed_api_client/__init__.py
ed_api_client/assignments.py
ed_api_client/canvas.py
ed_api_client/challenges.py
ed_api_client/client.py
ed_api_client/quizzes.py
ed_api_client/slides.py
ed_api_client/users.py
ed_api_client/websockets.py
ed_api_client/workspaces.py
ed_api_client-0.1.1.dist-info/METADATA
ed_api_client-0.1.1.dist-info/WHEEL
ed_api_client-0.1.1.dist-info/RECORD
