Metadata-Version: 2.3
Name: ed-api-client
Version: 0.1.1
Summary: A client for interacting with the Ed LMS
License: MIT
Author: David Milne
Author-email: d.n.milne@gmail.com
Requires-Python: >=3.6,<4.0
Classifier: License :: OSI Approved :: MIT License
Classifier: Programming Language :: Python :: 3
Classifier: Programming Language :: Python :: 3.6
Classifier: Programming Language :: Python :: 3.7
Classifier: Programming Language :: Python :: 3.8
Classifier: Programming Language :: Python :: 3.9
Classifier: Programming Language :: Python :: 3.10
Classifier: Programming Language :: Python :: 3.11
Classifier: Programming Language :: Python :: 3.12
Classifier: Programming Language :: Python :: 3.13
Requires-Dist: DateTime (>=5.1,<6.0)
Requires-Dist: dataclasses (==0.6)
Requires-Dist: pylcs (>=0.1.1,<0.2.0)
Requires-Dist: python-dateutil (>=2.9.0,<3.0.0)
Requires-Dist: requests (>=2.31.0,<3.0.0)
